LICENSE
README.md
setup.py
behat_config_leaks.egg-info/PKG-INFO
behat_config_leaks.egg-info/SOURCES.txt
behat_config_leaks.egg-info/dependency_links.txt
behat_config_leaks.egg-info/entry_points.txt
behat_config_leaks.egg-info/requires.txt
behat_config_leaks.egg-info/top_level.txt
behatconfigleaks/__init__.py
behatconfigleaks/main.py
behatconfigleaks/includes/__init__.py
behatconfigleaks/includes/bot.py
behatconfigleaks/includes/filereader.py
behatconfigleaks/includes/scan.py
behatconfigleaks/includes/writefile.py
behatconfigleaks/utils/__init__.py
behatconfigleaks/utils/configure.py
behatconfigleaks/utils/const.py
behatconfigleaks/utils/helpers.py
behatconfigleaks/utils/status.py